dy/DouYin.py
dy/__init__.py
jd/JingDong.py
jd/__init__.py
tm/TianMao.py
tm/__init__.py
utils/UserAgent.py
utils/__init__.py
utils/request.py
vip/Vip.py
vip/__init__.py
code_cui-1.0.dist-info/METADATA
code_cui-1.0.dist-info/WHEEL
code_cui-1.0.dist-info/top_level.txt
code_cui-1.0.dist-info/RECORD
