Metadata-Version: 2.1
Name: code-cui
Version: 1.0
Summary: 测试包
Author: cui
Author-email: codeCui@outlook.com
Classifier: Programming Language :: Python :: 3
Classifier: License :: OSI Approved :: MIT License
Classifier: Operating System :: OS Independent
Requires-Python: >=3
Requires-Dist: pillow
Requires-Dist: requests
